{
  "project_info": {
    "project_number": "540097408507",
    "project_id": "cpscom-acb3c",
    "storage_bucket": "cpscom-acb3c.appspot.com"
  },
  "client": [
    {
      "client_info": {
        "mobilesdk_app_id": "1:540097408507:android:895edb3158d5221011af5e",
        "android_client_info": {
          "package_name": "com.example.cpscom"
        }
      },
      "oauth_client": [
        {
          "client_id": "540097408507-bk7t77bk6rg4cahgutd0l8pt8dtvueuq.apps.googleusercontent.com",
          "client_type": 3
        }
      ],
      "api_key": [
        {
          "current_key": "AIzaSyAIzMTLwGHgVSwdc42vIS405e-8CWq78RY"
        }
      ],
      "services": {
        "appinvite_service": {
          "other_platform_oauth_client": [
            {
              "client_id": "540097408507-bk7t77bk6rg4cahgutd0l8pt8dtvueuq.apps.googleusercontent.com",
              "client_type": 3
            }
          ]
        }
      }
    }
  ],
  "configuration_version": "1"
}